b2a/__init__.py
b2a/aliplat.py
b2a/bdyplat.py
b2a/common.py
b2a/config.py
b2a/downloader.py
b2a/gui.py
b2a/platformImp.py
b2a/trans.py
b2a_gui/__init__.py
b2a_gui/download.py
b2a-2023.8.15.1.dist-info/METADATA
b2a-2023.8.15.1.dist-info/WHEEL
b2a-2023.8.15.1.dist-info/entry_points.txt
b2a-2023.8.15.1.dist-info/top_level.txt
b2a-2023.8.15.1.dist-info/RECORD
