Metadata-Version: 2.1
Name: b2a
Version: 2023.8.15.1
Summary: 迁移百度云到阿里云
Home-page: UNKNOWN
Author: Yaronzz
Author-email: yaronhuang@foxmail.com
License: MIT
Platform: any
Requires-Dist: aigpy
Requires-Dist: requests
Requires-Dist: tqdm
Requires-Dist: prettytable
Requires-Dist: Cython
Requires-Dist: BaiduPCS-Py
